INSTALL.rst
LICENSE
MANIFEST.in
README.rst
setup.py
xnet/__init__.py
xnet.egg-info/PKG-INFO
xnet.egg-info/SOURCES.txt
xnet.egg-info/dependency_links.txt
xnet.egg-info/entry_points.txt
xnet.egg-info/top_level.txt
xnet/debug/__init__.py
xnet/net/__init__.py
xnet/net/http/__init__.py
xnet/net/ipv4/__init__.py
xnet/net/ssh/__init__.py
xnet/packages/__init__.py
xnet/packages/urllib3/__init__.py
xnet/packages/urllib3/_collections.py
xnet/packages/urllib3/connectionpool.py
xnet/packages/urllib3/exceptions.py
xnet/packages/urllib3/filepost.py
xnet/packages/urllib3/poolmanager.py
xnet/packages/urllib3/request.py
xnet/packages/urllib3/response.py
xnet/packages/urllib3/util.py
xnet/packages/urllib3/packages/__init__.py
xnet/packages/urllib3/packages/ordered_dict.py
xnet/packages/urllib3/packages/six.py
xnet/packages/urllib3/packages/ssl_match_hostname/__init__.py
xnet/testing/__init__.py
xnet/testing/exceptions.py
xnet/tests/__init__.py
xnet/tests/all.py
xnet/tests/test_commandline.py
xnet/tests/test_ipv4.py
xnet/tools/__init__.py
xnet/tools/dummy.py
xnet/tools/iissn.py
xnet/tools/iprange.py
xnet/tools/netcats.py
xnet/tools/netfuzz.py
xnet/tools/resolv.py
xnet/tools/run.py
xnet/tools/seleniumtool.py
xnet/tools/sslinfo.py
xnet/tools/tcpclient.py
xnet/tools/tcpstate.py
xnet/tools/webget.py
xnet/tools/xinfo.py