Metadata-Version: 1.1
Name: xnet
Version: 0.3.0.2
Summary: XNet - Your Swiss Army Pitchfork of Networking
Home-page: http://xnet.tripleaes.com/
Author: Krister Hedfors
Author-email: krister.hedfors@gmail.com
License: LICENSE
Platform: UNKNOWN
Classifier: License :: OSI Approved
Classifier: License :: OSI Approved :: BSD License
Classifier: Programming Language :: Python
